pynetem/__init__.py
pynetem/main.py
pynetem/pynetem.py
pynetem/web.py
pynetem-0.1.5.data/data/README.md
pynetem-0.1.5.dist-info/LICENSE
pynetem-0.1.5.dist-info/METADATA
pynetem-0.1.5.dist-info/WHEEL
pynetem-0.1.5.dist-info/entry_points.txt
pynetem-0.1.5.dist-info/top_level.txt
pynetem-0.1.5.dist-info/RECORD
