Metadata-Version: 2.1
Name: pynetem
Version: 0.1.5
Summary: PyNetem is a tool that allow the user to limit the bandwidth or simulate weak network.
Home-page: https://github.com/GuoTengda1993/pynetem
Author: Guo Tengda
Author-email: ttguotengda@foxmail.com
License: MIT
Platform: UNKNOWN
Classifier: Topic :: Software Development :: Testing
Classifier: Development Status :: 4 - Beta
Classifier: License :: OSI Approved :: MIT License
Classifier: Operating System :: OS Independent
Classifier: Programming Language :: Python
Classifier: Programming Language :: Python :: 3.4
Classifier: Programming Language :: Python :: 3.5
Classifier: Programming Language :: Python :: 3.6
Classifier: Programming Language :: Python :: 3.7
Classifier: Programming Language :: Python :: 3.8
Classifier: Operating System :: POSIX
Classifier: Intended Audience :: Developers
Classifier: Intended Audience :: System Administrators
License-File: LICENSE
Requires-Dist: netifaces (>=0.10.0)
Requires-Dist: flask (>=1.0.0)
Requires-Dist: paramiko (>=1.7.0.0)
